{
    "icon": "fas-biking",
    "fields": [
        "crossing",
        "surface",
        "tactile_paving",
        "crossing/island",
        "crossing_raised",
        "access"
    ],
    "geometry": [
        "line"
    ],
    "tags": {
        "highway": "cycleway",
        "cycleway": "crossing",
        "crossing": "unmarked"
    },
    "addTags": {
        "highway": "cycleway",
        "cycleway": "crossing",
        "crossing": "unmarked",
        "crossing:markings": "no"
    },
    "reference": {
        "key": "crossing",
        "value": "unmarked"
    },
    "terms": [
        "bike crossing",
        "bicycle crossing",
        "cycle path crossing",
        "cycleway crossing"
    ],
    "matchScore": 0.95,
    "name": "Unmarked Cycle Crossing"
}
