{

    "icon": "maki-recycling",
    "fields": [
        "{amenity/recycling_centre}",
        "operator",
        "opening_hours",
        "collection_times"
    ],
    "moreFields": [
        "{amenity/recycling_centre}",    
        "website",     
        "landuse",
        "fee"
    ],
    "geometry": [
        "point",
        "area"
    ],
    "terms": [
        "recycling centre",
        "waste processing",
        "recycling"
    ],
    "tags": {
        "amenity": "recycling",
        "recycling_type": "centre"
    },
    "name": "Recycling Centre",
    "searchable": true
    
}