{
    "icon": "temaki-pedestrian_crosswalk",
    "fields": [
        "crossing",
        "access",
        "surface",
        "tactile_paving",
        "crossing/island"
    ],
    "geometry": [
        "line"
    ],
    "tags": {
        "highway": "footway",
        "footway": "crossing",
        "crossing": "marked"
    },
    "reference": {
        "key": "crossing",
        "value": "marked"
    },
    "terms": [
        "marked foot path crossing",
        "marked crossing",
        "marked pedestrian crosswalk",
        "zebra crossing"
    ],
    "name": "Marked Crosswalk"
}
