{
    "icon": "fas-house-medical-flag",
    "locationSet": {
        "include": ["ph"]
    },
    "fields": [
        "name",
        "operator",
        "address",
        "building_area_yes",
        "opening_hours"
    ],
    "moreFields": [
        "{@templates/poi}",
        "healthcare",
        "air_conditioning",
        "branch_brand",
        "brand"
    ],
    "geometry": [
        "point",
        "area"
    ],
    "terms": [
        "bhs",
        "health center"
    ],
    "tags": {
        "amenity": "health_post"
    },
    "addTags": {
        "healthcare": "community_health_worker",
        "operator:type": "government"
    },
    "reference": {
        "key": "amenity",
        "value": "health_post"
    },
    "name": "Barangay Health Station"
}
