{
    "icon": "maki-hospital",
    "fields": [
        "name",
        "kneipp_water_cure_multi",
        "access_simple",
        "opening_hours",
        "fee"
    ],
    "moreFields": [
        "address",
        "level",
        "wheelchair"
    ],
    "geometry": [
        "point",
        "area"
    ],
    "tags": {
        "amenity": "kneipp_water_cure"
    },
    "terms": [
        "foot bath",
        "hydrotherapy",
        "kneipp cure",
        "kneipp hydrotherapy",
        "kneippism"
    ],
    "name": "Kneipp Facility",
    "aliases": [
        "Kneipp Water Cure"
    ]
}
