{
    "icon": "temaki-cabin",
    "fields": [
        "name",
        "operator",
        "address",
        "phone",
        "building_area_yes",
        "{@templates/internet_access}",
        "fee",
        "payment_multi_fee",
        "charge_fee"
    ],
    "moreFields": [
        "{@templates/internet_access}",
        "{@templates/poi}",
        "reservation"
    ],
    "geometry": [
        "point",
        "area"
    ],
    "terms": [
        "cabin",
        "climbing hut",
        "lodge",
        "lodging",
        "overnight accommodations",
        "refuge",
        "refuge hut",
        "wilderness hut"
    ],
    "tags": {
        "tourism": "alpine_hut"
    },
    "name": "Mountain Lodge",
    "aliases": [
        "Alpine Hut",
        "Mountain Hut",
        "Mountain Shelter",
        "Mountain Refuge",
        "Mountain Hostel"
    ]
}
