{
    "keys": [
        "parking:both:orientation",
        "parking:left:orientation",
        "parking:righ:orientationt"
    ],
    "type": "directionalCombo",
    "label": "Parking orientation",
    "strings": {
        "types": {
            "parking:left:orientation": "Left side",
            "parking:right:orientation": "Right side",
            "parking:both:orientation": "Both sides"
        },
        "options": {
            "parallel": {
                "title": "Parallel to the Street",
                "description": "Parking "
            },
            "diagonal": {
                "title": "Diagonal in Relation to the Street",
                "description": ""
            },
            "perpendicular": {
                "title": "Meets the Street at a Straight Angle",
                "description": ""
            }
        }
    },
    "autoSuggestions": false,
    "customValues": false
}
