{
    "fields": [
        "bench",
        "bin",
        "informal",
        "shelter"
    ],
    "geometry": [
        "point"
    ],
    "tags": {
        "highway": "hitchhiking"
    },
    "terms": [
        "hitchhiking",
        "signed hitchhiking places",
        "thumbing"
    ],
    "locationSet": {
        "include": [
            "at",
            "ch",
            "de",
            "dk",
            "fx",
            "it",
            "li",
            "nl"
        ]
    },
    "name": "Signed Hitchhiking Place",
    "icon": "far-thumbs-up"
}
