{
    "key": "payment:",
    "type": "multiCombo",
    "label": "Payment Types",
    "strings": {
        "options": {
            "cash": "Cash",
            "coins": "Coins",
            "contactless": "Contactless Payment",
            "credit_cards": "Credit Card",
            "debit_cards": "Debit Card",
            "electronic_purses": "Electronic Purse",
            "notes": "Banknotes",
            "telephone_cards": "Telephone Card",
            "american_express": "American Express",
            "maestro": "Maestro",
            "mastercard": "Mastercard",
            "visa": "Visa",
            "visa_electron": "Visa Electron"
        }
    }
}
