{
    "key": "surface",
    "type": "combo",
    "label": "{surface}",
    "stringsCrossReference": "surface",
    "options": [
        "grass",
        "artificial_turf",
        "asphalt",
        "sand",
        "concrete",
        "clay",
        "tartan",
        "dirt",
        "compacted",
        "fine_gravel",
        "paving_stones",
        "sett",
        "unhewn_cobblestone",
        "grass_paver",
        "wood",
        "metal",
        "gravel",
        "pebblestone",
        "ground",
        "paved",
        "unpaved"
    ]
}
